moro/__init__.py
moro/abc.py
moro/core.py
moro/lib.py
moro/plotting.py
moro/transformations.py
moro/util.py
moro/version.py
moro/ws.py
moro-0.2.1.dist-info/LICENSE
moro-0.2.1.dist-info/METADATA
moro-0.2.1.dist-info/WHEEL
moro-0.2.1.dist-info/top_level.txt
moro-0.2.1.dist-info/RECORD
