Metadata-Version: 2.1
Name: moro
Version: 0.2.1
Summary: Python library for kinematic and dynamic modeling of robots
Home-page: https://github.com/numython-rd/moro
Author: Pedro Jorge De Los Santos
Author-email: delossantosmfq@gmail.com
License: MIT
Keywords: Robotics,Kinematics,Dynamics
Platform: UNKNOWN
Classifier: Development Status :: 2 - Pre-Alpha
Classifier: Intended Audience :: Education
Classifier: Intended Audience :: Developers
Classifier: License :: OSI Approved :: MIT License
Classifier: Operating System :: OS Independent
Classifier: Programming Language :: Python
Classifier: Programming Language :: Python :: 3.6
Classifier: Programming Language :: Python :: Implementation :: CPython
Requires-Dist: sympy
Requires-Dist: matplotlib
